hgvs/__init__.py
hgvs/alignmentmapper.py
hgvs/assemblymapper.py
hgvs/config.py
hgvs/easy.py
hgvs/edit.py
hgvs/enums.py
hgvs/exceptions.py
hgvs/hgvsposition.py
hgvs/intervalmapper.py
hgvs/location.py
hgvs/normalizer.py
hgvs/parser.py
hgvs/posedit.py
hgvs/projector.py
hgvs/repeats.py
hgvs/sequencevariant.py
hgvs/shell.py
hgvs/transcriptmapper.py
hgvs/validator.py
hgvs/variantmapper.py
hgvs/_data/defaults.ini
hgvs/_data/hgvs.pymeta
hgvs/_data/invitae.pymeta
hgvs/dataproviders/__init__.py
hgvs/dataproviders/interface.py
hgvs/dataproviders/ncbi.py
hgvs/dataproviders/seqfetcher.py
hgvs/dataproviders/uta.py
hgvs/decorators/__init__.py
hgvs/decorators/deprecated.py
hgvs/decorators/lru_cache.py
hgvs/extras/__init__.py
hgvs/extras/babelfish.py
hgvs/generated/__init__.py
hgvs/generated/hgvs_grammar.py
hgvs/pretty/datacompiler.py
hgvs/pretty/models.py
hgvs/pretty/prettyprint.py
hgvs/pretty/console/chromseqrenderer.py
hgvs/pretty/console/chromseqreverserenderer.py
hgvs/pretty/console/constants.py
hgvs/pretty/console/posinfo.py
hgvs/pretty/console/protmappingrenderer.py
hgvs/pretty/console/protrulerrenderer.py
hgvs/pretty/console/protseqrenderer.py
hgvs/pretty/console/renderer.py
hgvs/pretty/console/ruler.py
hgvs/pretty/console/shuffledvariant.py
hgvs/pretty/console/txaligrenderer.py
hgvs/pretty/console/txmappingrenderer.py
hgvs/pretty/console/txpos.py
hgvs/pretty/console/txrefdisagreerenderer.py
hgvs/utils/PersistentDict.py
hgvs/utils/__init__.py
hgvs/utils/altseq_to_hgvsp.py
hgvs/utils/altseqbuilder.py
hgvs/utils/cigarmapper.py
hgvs/utils/context.py
hgvs/utils/norm.py
hgvs/utils/orderedenum.py
hgvs/utils/reftranscriptdata.py
hgvs/utils/validation.py
hgvs-1.5.5.dist-info/licenses/AUTHORS
hgvs-1.5.5.dist-info/licenses/LICENSE.txt
hgvs-1.5.5.dist-info/METADATA
hgvs-1.5.5.dist-info/WHEEL
hgvs-1.5.5.dist-info/entry_points.txt
hgvs-1.5.5.dist-info/top_level.txt
hgvs-1.5.5.dist-info/zip-safe
hgvs-1.5.5.dist-info/RECORD
