Metadata-Version: 2.4
Name: hgvs
Version: 1.5.5
Summary: HGVS Parser, Formatter, Mapper, Validator
Author-email: HGVS Contributors <biocommons-dev@googlegroups.com>
License: 
Project-URL: Bug Tracker, https://github.com/biocommons/hgvs/issues
Project-URL: Homepage, https://github.com/biocommons/hgvs
Keywords: biocommons,bioinformatics,computational biology,genome variation,genomics,hgvs,variation
Classifier: Development Status :: 5 - Production/Stable
Classifier: Intended Audience :: Developers
Classifier: Intended Audience :: Healthcare Industry
Classifier: Intended Audience :: Science/Research
Classifier: License :: OSI Approved :: Apache Software License
Classifier: Operating System :: OS Independent
Classifier: Programming Language :: Python :: 3.10
Classifier: Programming Language :: Python :: 3.11
Classifier: Programming Language :: Python :: 3.12
Classifier: Programming Language :: Python :: 3
Classifier: Programming Language :: Python
Classifier: Topic :: Scientific/Engineering :: Bio-Informatics
Classifier: Topic :: Scientific/Engineering :: Medical Science Apps.
Requires-Python: >=3.10
License-File: LICENSE.txt
License-File: AUTHORS
Requires-Dist: attrs>=17.4.0
Requires-Dist: biocommons.seqrepo>=0.6.10
Requires-Dist: bioutils<1.0,>=0.4.0
Requires-Dist: configparser>=3.3.0
Requires-Dist: importlib_resources
Requires-Dist: ipython
Requires-Dist: parsley
Requires-Dist: pre-commit~=3.4
Requires-Dist: psycopg2
Provides-Extra: dev
Requires-Dist: black; extra == "dev"
Requires-Dist: flake8; extra == "dev"
Requires-Dist: ipython; extra == "dev"
Requires-Dist: isort; extra == "dev"
Requires-Dist: jupyter; extra == "dev"
Requires-Dist: pyright; extra == "dev"
Requires-Dist: pytest; extra == "dev"
Requires-Dist: pytest-cov; extra == "dev"
Requires-Dist: pytest-recording; extra == "dev"
Requires-Dist: restview; extra == "dev"
Requires-Dist: setuptools; extra == "dev"
Requires-Dist: sphinx; extra == "dev"
Requires-Dist: sphinx_rtd_theme; extra == "dev"
Requires-Dist: sphinxcontrib-fulltoc>=1.1; extra == "dev"
Requires-Dist: toml-sort; extra == "dev"
Requires-Dist: tox; extra == "dev"
Requires-Dist: vcrpy; extra == "dev"
Requires-Dist: yapf; extra == "dev"
Dynamic: license-file
